MANIFEST.in
README.rst
package.json
setup.cfg
setup.py
awsume/__init__.py
awsume/autoawsume.py
awsume/awsumepy.py
awsume/test_autoawsume.py
awsume/test_awsumepy.py
awsume/shellScripts/awsume
awsume/shellScripts/awsume.bat
awsume/shellScripts/awsume.ps1
rvs_awsume.egg-info/PKG-INFO
rvs_awsume.egg-info/SOURCES.txt
rvs_awsume.egg-info/dependency_links.txt
rvs_awsume.egg-info/entry_points.txt
rvs_awsume.egg-info/requires.txt
rvs_awsume.egg-info/top_level.txt