Metadata-Version: 1.0
Name: rvs-awsume
Version: 3.2.8.6
Summary: Awsume - A cli that makes using AWS IAM credentials easy
Home-page: https://github.com/vetaljanos/awsume
Author: Trek10, Inc
Author-email: package-management@trek10.com
License: MIT
Platform: UNKNOWN
